pyscopg2_utility_functions/__init__.py
pyscopg2_utility_functions/pyscopg2_utility_functions.py
pyscopg2_utility_functions/test.py
psycopg2_utility_functions-0.0.13.dist-info/LICENSE
psycopg2_utility_functions-0.0.13.dist-info/METADATA
psycopg2_utility_functions-0.0.13.dist-info/WHEEL
psycopg2_utility_functions-0.0.13.dist-info/top_level.txt
psycopg2_utility_functions-0.0.13.dist-info/RECORD
